{"tracking":[{"gps_latitude":"6.2752026","added_date":"2014-12-08 03:12:23","battry_level":"11","gps_longitude":"80.630387"},{"gps_latitude":"6.2842962","added_date":"2014-12-08 03:12:23","battry_level":"11","gps_longitude":"80.6343414"},{"gps_latitude":"6.2842962","added_date":"2014-12-08 03:12:23","battry_level":"11","gps_longitude":"80.6343414"},{"gps_latitude":"6.2842962","added_date":"2014-12-08 03:12:23","battry_level":"11","gps_longitude":"80.6343414"},{"gps_latitude":"6.2842962","added_date":"2014-12-08 03:12:47","battry_level":"11","gps_longitude":"80.6343414"},{"gps_latitude":"6.2842962","added_date":"2014-12-08 04:12:56","battry_level":"11","gps_longitude":"80.6343414"},{"gps_latitude":"6.2842962","added_date":"2014-12-08 04:12:56","battry_level":"11","gps_longitude":"80.6343414"},{"gps_latitude":"6.2752026","added_date":"2014-12-08 04:12:56","battry_level":"11","gps_longitude":"80.630387"},{"gps_latitude":"6.2797494","added_date":"2014-12-08 04:12:56","battry_level":"11","gps_longitude":"80.6323642"},{"gps_latitude":"6.2797494","added_date":"2014-12-08 04:12:56","battry_level":"11","gps_longitude":"80.6323642"},{"gps_latitude":"6.2797494","added_date":"2014-12-08 04:12:57","battry_level":"11","gps_longitude":"80.6323642"},{"gps_latitude":"6.2752026","added_date":"2014-12-08 04:12:57","battry_level":"11","gps_longitude":"80.630387"},{"gps_latitude":"6.2752026","added_date":"2014-12-08 04:12:59","battry_level":"11","gps_longitude":"80.630387"},{"gps_latitude":"6.2752026","added_date":"2014-12-08 04:12:28","battry_level":"11","gps_longitude":"80.630387"},{"gps_latitude":"6.2752026","added_date":"2014-12-08 04:12:28","battry_level":"10","gps_longitude":"80.630387"},{"gps_latitude":"6.2752026","added_date":"2014-12-08 04:12:28","battry_level":"10","gps_longitude":"80.630387"}]}