{"tracking":[{"gps_latitude":"6.608521666666666","added_date":"2014-11-05 04:11:17","battry_level":"73","gps_longitude":"79.95249"},{"gps_latitude":"6.608498333333333","added_date":"2014-11-05 04:11:17","battry_level":"73","gps_longitude":"79.95245333333334"},{"gps_latitude":"6.612681666666667","added_date":"2014-11-05 04:11:17","battry_level":"73","gps_longitude":"79.94960333333333"},{"gps_latitude":"6.618456666666667","added_date":"2014-11-05 04:11:17","battry_level":"73","gps_longitude":"79.94741833333333"},{"gps_latitude":"6.620741666666667","added_date":"2014-11-05 04:11:17","battry_level":"73","gps_longitude":"79.94646666666667"},{"gps_latitude":"6.621605","added_date":"2014-11-05 04:11:17","battry_level":"73","gps_longitude":"79.945995"},{"gps_latitude":"6.624305","added_date":"2014-11-05 04:11:17","battry_level":"73","gps_longitude":"79.94453833333334"},{"gps_latitude":"6.62884","added_date":"2014-11-05 04:11:17","battry_level":"73","gps_longitude":"79.94317"},{"gps_latitude":"6.632996666666666","added_date":"2014-11-05 04:11:17","battry_level":"73","gps_longitude":"79.94158166666666"},{"gps_latitude":"6.639311666666667","added_date":"2014-11-05 04:11:17","battry_level":"73","gps_longitude":"79.93913833333333"},{"gps_latitude":"6.644416666666666","added_date":"2014-11-05 04:11:18","battry_level":"73","gps_longitude":"79.93805166666667"},{"gps_latitude":"6.647919999999999","added_date":"2014-11-05 04:11:18","battry_level":"73","gps_longitude":"79.93658"},{"gps_latitude":"6.652843333333334","added_date":"2014-11-05 04:11:18","battry_level":"73","gps_longitude":"79.93506833333332"},{"gps_latitude":"6.65865","added_date":"2014-11-05 04:11:18","battry_level":"73","gps_longitude":"79.93316333333334"},{"gps_latitude":"6.6629233333333335","added_date":"2014-11-05 04:11:18","battry_level":"73","gps_longitude":"79.93091833333332"}]}