{"tracking":[{"gps_latitude":"6.687079999999999","added_date":"2014-11-11 10:11:14","battry_level":"85","gps_longitude":"79.91866333333334"},{"gps_latitude":"6.681433333333333","added_date":"2014-11-11 10:11:14","battry_level":"85","gps_longitude":"79.92133333333332"},{"gps_latitude":"6.676463333333333","added_date":"2014-11-11 10:11:14","battry_level":"85","gps_longitude":"79.92395"},{"gps_latitude":"6.670668333333333","added_date":"2014-11-11 10:11:14","battry_level":"85","gps_longitude":"79.92731833333333"},{"gps_latitude":"6.664768333333335","added_date":"2014-11-11 10:11:14","battry_level":"85","gps_longitude":"79.93021"},{"gps_latitude":"6.66048","added_date":"2014-11-11 10:11:14","battry_level":"85","gps_longitude":"79.93234833333332"},{"gps_latitude":"6.654248333333333","added_date":"2014-11-11 10:11:14","battry_level":"85","gps_longitude":"79.934795"},{"gps_latitude":"6.647474999999999","added_date":"2014-11-11 10:11:14","battry_level":"85","gps_longitude":"79.93657166666667"},{"gps_latitude":"6.642075","added_date":"2014-11-11 10:11:14","battry_level":"85","gps_longitude":"79.939275"},{"gps_latitude":"6.635121666666667","added_date":"2014-11-11 10:11:14","battry_level":"85","gps_longitude":"79.94092500000001"},{"gps_latitude":"6.628511666666666","added_date":"2014-11-11 10:11:14","battry_level":"85","gps_longitude":"79.94339666666666"},{"gps_latitude":"6.622741666666667","added_date":"2014-11-11 10:11:14","battry_level":"85","gps_longitude":"79.94546833333334"},{"gps_latitude":"6.615815","added_date":"2014-11-11 10:11:14","battry_level":"85","gps_longitude":"79.94839"},{"gps_latitude":"6.608980000000001","added_date":"2014-11-11 10:11:14","battry_level":"85","gps_longitude":"79.95237999999999"},{"gps_latitude":"6.601783333333333","added_date":"2014-11-11 10:11:14","battry_level":"84","gps_longitude":"79.955785"}]}