{"tracking":[{"gps_latitude":"9.8013046","added_date":"2014-10-08 12:10:08","battry_level":"45","gps_longitude":"80.197592"},{"gps_latitude":"9.8011222","added_date":"2014-10-08 12:10:08","battry_level":"45","gps_longitude":"80.1978149"},{"gps_latitude":"9.7958388","added_date":"2014-10-08 12:10:08","battry_level":"43","gps_longitude":"80.1856394"},{"gps_latitude":"9.805533333333333","added_date":"2014-10-08 12:10:08","battry_level":"42","gps_longitude":"80.18991833333332"},{"gps_latitude":"9.805498333333333","added_date":"2014-10-08 12:10:08","battry_level":"41","gps_longitude":"80.19005166666668"},{"gps_latitude":"9.805538333333335","added_date":"2014-10-08 12:10:08","battry_level":"41","gps_longitude":"80.18993833333334"},{"gps_latitude":"9.805506666666668","added_date":"2014-10-08 12:10:08","battry_level":"41","gps_longitude":"80.19005"},{"gps_latitude":"9.805563333333334","added_date":"2014-10-08 12:10:08","battry_level":"41","gps_longitude":"80.19001666666666"},{"gps_latitude":"9.805611666666666","added_date":"2014-10-08 12:10:08","battry_level":"41","gps_longitude":"80.190025"},{"gps_latitude":"9.805591666666666","added_date":"2014-10-08 12:10:08","battry_level":"40","gps_longitude":"80.19000166666666"},{"gps_latitude":"9.80569","added_date":"2014-10-08 12:10:08","battry_level":"39","gps_longitude":"80.19014166666666"},{"gps_latitude":"9.805536666666665","added_date":"2014-10-08 12:10:08","battry_level":"38","gps_longitude":"80.19016333333335"},{"gps_latitude":"9.805386666666667","added_date":"2014-10-08 12:10:08","battry_level":"37","gps_longitude":"80.18902666666666"},{"gps_latitude":"9.7967298","added_date":"2014-10-08 12:10:08","battry_level":"35","gps_longitude":"80.183286"},{"gps_latitude":"9.8009398","added_date":"2014-10-08 01:10:08","battry_level":"34","gps_longitude":"80.1980378"},{"gps_latitude":"9.8013046","added_date":"2014-10-08 01:10:08","battry_level":"33","gps_longitude":"80.197592"}]}