{"tracking":[{"gps_latitude":"6.731425","added_date":"2014-10-21 11:10:16","battry_level":"81","gps_longitude":"79.906955"},{"gps_latitude":"6.731425","added_date":"2014-10-21 11:10:16","battry_level":"80","gps_longitude":"79.906955"},{"gps_latitude":"6.731425","added_date":"2014-10-21 11:10:16","battry_level":"80","gps_longitude":"79.906955"},{"gps_latitude":"6.731425","added_date":"2014-10-21 11:10:16","battry_level":"80","gps_longitude":"79.906955"},{"gps_latitude":"6.731425","added_date":"2014-10-21 11:10:16","battry_level":"80","gps_longitude":"79.906955"},{"gps_latitude":"6.731425","added_date":"2014-10-21 11:10:16","battry_level":"80","gps_longitude":"79.906955"},{"gps_latitude":"6.731425","added_date":"2014-10-21 11:10:16","battry_level":"80","gps_longitude":"79.906955"},{"gps_latitude":"6.731425","added_date":"2014-10-21 11:10:16","battry_level":"80","gps_longitude":"79.906955"},{"gps_latitude":"6.731425","added_date":"2014-10-21 11:10:16","battry_level":"80","gps_longitude":"79.906955"},{"gps_latitude":"6.731425","added_date":"2014-10-21 11:10:16","battry_level":"80","gps_longitude":"79.906955"},{"gps_latitude":"6.731425","added_date":"2014-10-21 11:10:16","battry_level":"80","gps_longitude":"79.906955"},{"gps_latitude":"6.731425","added_date":"2014-10-21 11:10:16","battry_level":"80","gps_longitude":"79.906955"},{"gps_latitude":"6.731425","added_date":"2014-10-21 11:10:16","battry_level":"80","gps_longitude":"79.906955"},{"gps_latitude":"6.731425","added_date":"2014-10-21 11:10:16","battry_level":"80","gps_longitude":"79.906955"},{"gps_latitude":"6.731425","added_date":"2014-10-21 11:10:16","battry_level":"80","gps_longitude":"79.906955"}]}