{"tracking":[{"gps_latitude":"6.273361666666667","added_date":"2014-10-20 01:10:27","battry_level":"16","gps_longitude":"80.174325"},{"gps_latitude":"6.273056666666667","added_date":"2014-10-20 01:10:27","battry_level":"16","gps_longitude":"80.17297"},{"gps_latitude":"6.272519999999999","added_date":"2014-10-20 01:10:27","battry_level":"16","gps_longitude":"80.17275333333333"},{"gps_latitude":"6.272519999999999","added_date":"2014-10-20 02:10:27","battry_level":"16","gps_longitude":"80.17275333333333"},{"gps_latitude":"6.272519999999999","added_date":"2014-10-20 02:10:27","battry_level":"16","gps_longitude":"80.17275333333333"},{"gps_latitude":"6.272519999999999","added_date":"2014-10-20 02:10:27","battry_level":"16","gps_longitude":"80.17275333333333"},{"gps_latitude":"6.272519999999999","added_date":"2014-10-20 02:10:27","battry_level":"16","gps_longitude":"80.17275333333333"},{"gps_latitude":"6.272519999999999","added_date":"2014-10-20 02:10:27","battry_level":"16","gps_longitude":"80.17275333333333"},{"gps_latitude":"6.27245","added_date":"2014-10-20 02:10:27","battry_level":"16","gps_longitude":"80.17280833333332"},{"gps_latitude":"6.27245","added_date":"2014-10-20 02:10:27","battry_level":"16","gps_longitude":"80.17280833333332"},{"gps_latitude":"6.27245","added_date":"2014-10-20 02:10:27","battry_level":"16","gps_longitude":"80.17280833333332"},{"gps_latitude":"6.27245","added_date":"2014-10-20 02:10:27","battry_level":"16","gps_longitude":"80.17280833333332"},{"gps_latitude":"6.27245","added_date":"2014-10-20 02:10:27","battry_level":"16","gps_longitude":"80.17280833333332"},{"gps_latitude":"6.27245","added_date":"2014-10-20 02:10:27","battry_level":"16","gps_longitude":"80.17280833333332"},{"gps_latitude":"6.27245","added_date":"2014-10-20 02:10:27","battry_level":"16","gps_longitude":"80.17280833333332"}]}